guidelines/__init__.py
guidelines/__main__.py
guidelines/base.py
guidelines-0.0.2.dist-info/LICENSE
guidelines-0.0.2.dist-info/METADATA
guidelines-0.0.2.dist-info/WHEEL
guidelines-0.0.2.dist-info/entry_points.txt
guidelines-0.0.2.dist-info/top_level.txt
guidelines-0.0.2.dist-info/RECORD
