Metadata-Version: 2.1
Name: guidelines
Version: 0.0.2
Summary: Awesome guidelines created by medinfox
Home-page: https://github.com/medinfox/guidelines/
Author: medinfox
License-File: LICENSE
Requires-Dist: tqdm
Provides-Extra: test
Requires-Dist: pytest; extra == "test"
Requires-Dist: coverage; extra == "test"
Requires-Dist: flake8; extra == "test"
Requires-Dist: black; extra == "test"
Requires-Dist: isort; extra == "test"
Requires-Dist: pytest-cov; extra == "test"
Requires-Dist: mypy; extra == "test"
Requires-Dist: gitchangelog; extra == "test"
Requires-Dist: mkdocs; extra == "test"
